massiviu/__init__.py
massiviu/configure_app.py
massiviu/context.py
massiviu/db_context.py
massiviu/exceptions.py
massiviu/item_cache.py
massiviu/model_context.py
massiviu/operations.py
massiviu/testsuite.py
massiviu-0.1.0.dist-info/DESCRIPTION.rst
massiviu-0.1.0.dist-info/METADATA
massiviu-0.1.0.dist-info/RECORD
massiviu-0.1.0.dist-info/WHEEL
massiviu-0.1.0.dist-info/metadata.json
massiviu-0.1.0.dist-info/top_level.txt
