Metadata-Version: 2.0
Name: massiviu
Version: 0.1.0
Summary: MassivIU - Simplified "bulk" insert/update/delete for Django.
Home-page: https://github.com/weholt/massiviu
Author: Thomas Weholt
Author-email: thomas@weholt.org
License: UNKNOWN
Platform: UNKNOWN
Classifier: Development Status :: 4 - Beta
Classifier: Intended Audience :: Developers
Classifier: Framework :: Django
Classifier: License :: OSI Approved :: BSD License
Classifier: Operating System :: OS Independent
Classifier: Programming Language :: Python
Classifier: Topic :: Database
Requires: django
